odoo/addons/role_policy_demo/README.rst
odoo/addons/role_policy_demo/__init__.py
odoo/addons/role_policy_demo/__manifest__.py
odoo/addons/role_policy_demo/data/res_role_data.xml
odoo/addons/role_policy_demo/data/res_user_data.xml
odoo/addons/role_policy_demo/data/web_modifier_rule_data.xml
odoo/addons/role_policy_demo/i18n/role_policy_demo.pot
odoo/addons/role_policy_demo/readme/CONFIGURE.rst
odoo/addons/role_policy_demo/readme/CONTRIBUTORS.rst
odoo/addons/role_policy_demo/readme/DESCRIPTION.rst
odoo/addons/role_policy_demo/static/description/icon.png
odoo/addons/role_policy_demo/static/description/index.html
odoo13_addon_role_policy_demo-13.0.1.0.1.dev10.dist-info/METADATA
odoo13_addon_role_policy_demo-13.0.1.0.1.dev10.dist-info/WHEEL
odoo13_addon_role_policy_demo-13.0.1.0.1.dev10.dist-info/top_level.txt
odoo13_addon_role_policy_demo-13.0.1.0.1.dev10.dist-info/RECORD
